DS18B20dvr/DS18B20.py
DS18B20dvr/__init__.py
ds18b20dvr-1.2.2.dist-info/licenses/LICENSE.txt
ds18b20dvr-1.2.2.dist-info/METADATA
ds18b20dvr-1.2.2.dist-info/WHEEL
ds18b20dvr-1.2.2.dist-info/entry_points.txt
ds18b20dvr-1.2.2.dist-info/top_level.txt
ds18b20dvr-1.2.2.dist-info/RECORD
