Metadata-Version: 2.4
Name: DS18B20dvr
Version: 1.2.2
Summary: DS18B20 library/driver for Raspberry Pi using the w1_therm kernel driver
Author-email: Chris Nelson <github@cjnaz.com>
License-Expression: MIT
Project-URL: repository, https://github.com/cjnaz/DS18B20
Keywords: cjnaz,ds18b20,driver
Classifier: Programming Language :: Python :: 3
Classifier: Topic :: System :: Hardware :: Hardware Drivers
Requires-Python: >=3.7
License-File: LICENSE.txt
Dynamic: license-file
